datasieve/__init__.py
datasieve/pipeline.py
datasieve/transforms/__init__.py
datasieve/transforms/base_transform.py
datasieve/transforms/dbscan.py
datasieve/transforms/dissimilarity_index.py
datasieve/transforms/noise.py
datasieve/transforms/pca.py
datasieve/transforms/sklearn_wrapper.py
datasieve/transforms/svm_outlier_extractor.py
datasieve/transforms/variance_threshold.py
datasieve/utils.py
datasieve-0.1.7.dist-info/LICENSE
datasieve-0.1.7.dist-info/METADATA
datasieve-0.1.7.dist-info/WHEEL
datasieve-0.1.7.dist-info/RECORD
