Metadata-Version: 2.1
Name: datasieve
Version: 0.1.7
Summary: This package implements a flexible data pipeline to help organize row removal (e.g. outlier removal) and feature modification (e.g. PCA)
License: MIT
Author: Robert Caulk
Requires-Python: >=3.8.1,<4.0
Classifier: License :: OSI Approved :: MIT License
Classifier: Programming Language :: Python :: 3
Classifier: Programming Language :: Python :: 3.9
Classifier: Programming Language :: Python :: 3.10
Classifier: Programming Language :: Python :: 3.11
Requires-Dist: pandas (>=2.0.3)
Requires-Dist: scikit-learn (>=1.1.3)
